setup.py
receptive/__init__.py
receptive.egg-info/PKG-INFO
receptive.egg-info/SOURCES.txt
receptive.egg-info/dependency_links.txt
receptive.egg-info/not-zip-safe
receptive.egg-info/top_level.txt