Metadata-Version: 1.0
Name: receptive
Version: 1.1
Summary: Receptive integration for Python
Home-page: https://github.com/Receptive/receptive-python
Author: Dan Dukeson
Author-email: dan@receptive.io
License: MIT
Platform: UNKNOWN
